[
    {
        "id": 1,
        "email": "j.doe@test.com",
        "username": "jdoe",
        "role_id": 1,
        "password": "password",
        "first_name": "John",
        "last_name": "Doe",
        "status": "active"
    },
    {
        "id": 2,
        "email": "j.smith@test.com",
        "username": "jsmith",
        "role_id": 1,
        "password": "password",
        "first_name": "John",
        "last_name": "Smith",
        "status": "active"
    },
    {
        "id": 3,
        "email": "jane.doe@test.com",
        "username": "janedoe",
        "role_id": 3,
        "password": "password",
        "first_name": "Jane",
        "last_name": "Doe",
        "status": "active"
    }
]